Metadata-Version: 2.1
Name: scrapgpt
Version: 1.1.0
Summary: Python library for scraping ChatGPT
Author: Dusk Light
Project-URL: Documentation, https://github.com/dusklight00/scrapgpt
